{"card_name": "Cone of Lightning", "color": "R", "rarity": "cube", "type": "Sorcery", "number": 141, "color_identity": "R", "cost": "{2}{R}", "rules_text": "As an additional cost to cast this spell, return a land you control to its owner's hand.\nCone of Lightning deals 3 damage divided as you choose among one, two, or three targets.", "flavor_text": "[i][/i]", "pt": "", "special_text": "", "shape": "normal", "set": "RCC25", "loyalty": "", "artist": "Midjourney (TGR)", "notes": "", "image_type": "png"}