{"card_name": "Relentless Advancement", "color": "R", "rarity": "cube", "type": "Enchantment", "number": 164, "color_identity": "R", "cost": "{1}{R}", "rules_text": "Vanishing 3 [i](This permanent enters with three time counters on it. At the beginning of your upkeep, remove a time counter from it. When the last is removed, sacrifice it.)[/i]\nWhen this enchantment enters and each time you remove a time counter from it, create a 2/2 black Zombie creature token with \u201cThis token can't block.\u201d That token gains haste until end of turn.", "flavor_text": "[i][/i]", "pt": "", "special_text": "", "shape": "normal", "set": "RCC25", "loyalty": "", "artist": "Peter Polach", "notes": "!tag TWE", "image_type": "png"}