{"card_name": "Earthshaker Beast", "color": "G", "rarity": "cube", "type": "Creature \u2013 Beast", "number": 190, "color_identity": "G", "cost": "{6}{G}{G}{G}", "rules_text": "Delve [i](Each card you exile from your graveyard while casting this spell pays for {1}.)[/i]\nTrample, haste\nWhen this creature enters, it and up to two other target creatures you control each get +3/+3 until end of turn.", "flavor_text": "[i][/i]", "pt": "6/4", "special_text": "", "shape": "normal", "set": "RCC25", "loyalty": "", "artist": "Midjourney (Caves of Orana)", "notes": "!tag COO", "image_type": "png"}