{"card_name": "Relic Hog", "color": "BG", "rarity": "cube", "type": "Creature \u2013 Boar", "number": 284, "color_identity": "BG", "cost": "{2}{BG}", "rules_text": "Whenever this creature enters or dies, you gain 2 life and create a Salvage token. [i](It's an artifact with \u201c{1}, {T}, Sacrifice this: Reveal the top card of your library. If it's a land card, draw it. Otherwise, you may mill it.\u201d)[/i]", "flavor_text": "[i][/i]", "pt": "3/3", "special_text": "", "shape": "normal", "set": "RCC25", "loyalty": "", "artist": "Midjourney (TGR)", "notes": "!tag TGR", "image_type": "png"}