{"card_name": "Longshot Bot", "color": "R", "rarity": "rare", "type": "Artifact Creature \u2013 Construct", "number": 151, "color_identity": "R", "cost": "{3}{R}", "rules_text": "Reach\nWhen this creature enters, it deals damage to target creature or planeswalker an opponent controls equal to the number of artifacts you control.", "flavor_text": "[i]\u201cYou learn a little paranoia is warranted over the course of a thousand years.\u201d\n\u2014Junklord Vorrick[/i]", "pt": "3/2", "special_text": "", "shape": "normal", "set": "WGJ", "loyalty": "", "artist": "Zack Jones", "notes": "#red #rare", "image_type": "png"}