{"card_name": "Sevrox, Ascended", "color": "", "rarity": "mythic", "type": "Legendary Planeswalker \u2013 Sevrox", "number": 1, "color_identity": "WUBRG", "cost": "{5}", "rules_text": "", "flavor_text": "[i][/i]", "pt": "", "special_text": "At the beginning of each end step, you may activate one of Sevrox's loyalty abilities if you spent {W}{U}{B}{R}{G} to cast spells this turn.\n[+1]: Surveil 1, then draw a card.\n[-3]: Destroy target creature. Its controller creates a Junk token.\n[-6]: Create a token that's a copy of Sevrox, except it's not legendary", "shape": "planeswalker", "set": "WGJ", "loyalty": "4", "artist": "Dimitar Katsarov", "notes": "!tokens Junk\n\n#colorless #mythic #planeswalker", "image_type": "png"}