{"card_name": "CW02 Industrious Urchins", "color": "W", "rarity": "common", "type": "Creature \u2013 Human Rebel Scout", "number": 2, "color_identity": "W", "cost": "{1}{W}", "rules_text": "Lifelink\n[i]Revolt[/i] \u2013 When this creature enters, if a permanent you controlled left the battlefield this turn, create a 1/1 red Rebel creature token.", "flavor_text": "[i][/i]", "pt": "1/3", "special_text": "", "shape": "normal", "set": "RBL", "loyalty": "", "artist": "keita kobayashi", "notes": "#white #common", "image_type": "png"}