{"card_name": "Heart of Artichokes", "color": "G", "rarity": "cube", "type": "Creature \u2013 Spirit Elk", "number": 141, "color_identity": "G", "cost": "{1}{G}", "rules_text": "{1}{G}, Sacrifice a nonland, noncreature permanent: Put a +1/+1 counter on this creature.\nWhen this creature attacks, if you've sacrificed a nonland, noncreature permanent this turn, create a green 1/2 plant with defender.", "flavor_text": "[i][/i]", "pt": "2/2", "special_text": "", "shape": "normal", "set": "POPCORN", "loyalty": "", "artist": "", "notes": "Needs_Art", "image_type": "png"}