{"card_name": "Stir the Wilds", "color": "UG", "rarity": "cube", "type": "Enchantment \u2013 Aura", "number": 210, "color_identity": "UG", "cost": "{1}{G}{U}", "rules_text": "Enchanted land is a 4/4 creature in addition to its other types. \nEnchanted land has \u201cLand creatures you control have haste and trample.\u201d", "flavor_text": "[i][/i]", "pt": "", "special_text": "", "shape": "normal", "set": "POPCORN", "loyalty": "", "artist": "", "notes": "Needs_Art\n\nRank 3 - just a templating question. Should the second ability be static instead of granting it to the land? Not sure what's more common in canon", "image_type": "png"}