{"card_name": "Riveted Climb", "color": "", "rarity": "cube", "type": "Artifact Land \u2013 Vehicle", "number": 291, "color_identity": "WU", "cost": "", "rules_text": "This land enters tapped.\nVigilance\n{T}: Add {W} or {U}.\nCrew 1 [i](Tap any number of creatures you control with total power 1 or more: This Vehicle becomes an artifact creature until end of turn.)[/i]", "flavor_text": "[i][/i]", "pt": "2/3", "special_text": "", "shape": "normal", "set": "POPCORN", "loyalty": "", "artist": "Hao Wang", "notes": "ARTed\n\n!tag Vehicle-Duals", "image_type": "png"}