{"card_name": "Portis, the Dawncaller", "color": "B", "rarity": "cube", "type": "Creature \u2013 Skeleton Dragon", "number": 104, "color_identity": "B", "cost": "{5}{B}{B}", "rules_text": "Flying\nWhen this creature enters, exile any number of cards from your graveyard. For each creature card exiled this way, create a 1/1 white Bird creature token with flying.\nYou may cast noncreature cards exiled by this creature.\nWhen you cast a card you own from exile, draw a card and lose 1 life.", "flavor_text": "[i][/i]", "pt": "7/7", "special_text": "", "shape": "normal", "set": "POP", "loyalty": "", "artist": "Bram Willemot", "notes": "!tag MonoWhiteBorder\n!token Bird", "image_type": "png"}