{"card_name": "Ikorran, Dragonmaster", "color": "R", "rarity": "cube", "type": "Legendary Planeswalker \u2013 Ikorran", "number": 132, "color_identity": "R", "cost": "{2}{R}{R}", "rules_text": "", "flavor_text": "[i][/i]", "pt": "", "special_text": "Whenever a Dragon you control enters, you may activate a loyalty ability of Ikorran. This ability triggers only once each turn.\n[+1]: Create a tapped Mountain land token.\n[-2]: This planeswalker deals 2 damage to any target.\n[-8]: You get an emblem with \u201cAt the beginning of your upkeep, search your library for a Dragon card, reveal it, put it into your hand, then shuffle.\u201d", "shape": "planeswalker", "set": "POP", "loyalty": "4", "artist": "Omar Valleios", "notes": "!tag Redbay\n!tokens Mountain", "image_type": "png"}