{"card_name": "Summer Salsa", "color": "R", "rarity": "cube", "type": "Enchantment \u2013 Saga", "number": 146, "color_identity": "R", "cost": "{1}{R}{R}", "rules_text": "", "flavor_text": "[i][/i]", "pt": "", "special_text": "[i](As this Saga enters and after your draw step, add a lore counter. Sacrifice after III.)[/i]\nI, II \u2013 Exile the top card of your library. You may play that card from exile for as long as you control this Saga.\nIII \u2013 Create a tapped Treasure token for each card type among cards you own in exile.\n\u200b", "shape": "saga", "set": "POP", "loyalty": "", "artist": "AtmosphericKitten", "notes": "!tag Pat\n!tokens Treasure", "image_type": "png"}