{"card_name": "Siege Tank", "color": "WR", "rarity": "cube", "type": "Artifact Creature \u2013 Fortification Construct", "number": 248, "color_identity": "WR", "cost": "{4}{R}{W}", "rules_text": "Whenever this creature attacks or fortified land becomes tapped, it deals 3 damage to target player, planeswalker or battle.\nStabilize {4} [i]({4}: Attach to target land you control; or unattach from a land. Reconfigure only as a sorcery. While attached, this isn't a creature.)[/i]", "flavor_text": "[i]\u201cReady to roll out!\u201d[/i]", "pt": "4/6", "special_text": "", "shape": "normal", "set": "POP", "loyalty": "", "artist": "Marko Ivanovic", "notes": "!tag Redbay", "image_type": "png"}