{"card_name": "UB01 Vengeful Shinobi", "color": "B", "rarity": "uncommon", "type": "Creature \u2013 Rabbit Ninja", "number": 103, "color_identity": "B", "cost": "{B}", "rules_text": "Third Act [i](If your life total is less than half of your starting life total or if you have one or fewer cards in hand, you enter the Third Act for the rest of the game.)[/i]\nDeathtouch\nAt the beginning of your end step, if you're in you third act, put a +1/+1 counter on this creature.", "flavor_text": "[i][/i]", "pt": "1/1", "special_text": "", "shape": "normal", "set": "FILM", "loyalty": "", "artist": "Ricardo Caria", "notes": "#uncommon #black", "image_type": "png"}